Workbook
Name Inventory: Sales_Data!$J$2:$J$144
Name Weekly_Sales: Sales_Data!$D$2:$D$144

Sheet Sales_Data
A1: Store | B1: Dept | C1: Date | D1: Weekly_Sales | E1: IsHoliday | F1: Year | G1: Month | H1: Month_Year | I1: Week_No | J1: Inventory_Level | K1: 3_Week_Forecast | L1: Forecast Error | M1: Absolute Percentage Error | N1: Store_Date_Key | O1: Temperature | P1: CPI | Q1: Total Markdown | R1: Forecast Check
A2: 1 | B2: 1 | C2: 40214 | D2: 24924.5 | E2: FALSE | F2: =YEAR(Table2[[#This Row],[Date]]) -> 2010 | G2: =TEXT(Table2[[#This Row],[Date]],"mmm") -> Feb | H2: =TEXT(Table2[[#This Row],[Date]],"yyyy-mm") -> 2010-02 | I2: =WEEKNUM(Table2[[#This Row],[Date]]) -> 6 | J2: =Table2[[#This Row],[Weekly_Sales]]*2 -> 49849 | N2: =Table2[[#This Row],[Store]] & "_" & TEXT(Table2[[#This Row],[Date]],"yyyy-mm-dd") -> 1_2010-02-05 | O2: =VLOOKUP($N2,Features!A2:N144,4,FALSE) -> 42.31 | P2: =VLOOKUP($N2,Features!A2:N144,11,FALSE) -> 211.09636 | Q2: =VLOOKUP($N2,Features!A2:N144,14,FALSE) -> 0 | R2: =IF(Table2[[#This Row],[3_Week_Forecast]]<Table2[[#This Row],[Weekly_Sales]], "Underforecast", "Overforecast") -> Underforecast | T2: KPIs
A3: 1 | B3: 1 | C3: 40221 | D3: 46039.49 | E3: TRUE | F3: =YEAR(Table2[[#This Row],[Date]]) -> 2010 | G3: =TEXT(Table2[[#This Row],[Date]],"mmm") -> Feb | H3: =TEXT(Table2[[#This Row],[Date]],"yyyy-mm") -> 2010-02 | I3: =WEEKNUM(Table2[[#This Row],[Date]]) -> 7 | J3: =Table2[[#This Row],[Weekly_Sales]]*2 -> 92078.98 | N3: =Table2[[#This Row],[Store]] & "_" & TEXT(Table2[[#This Row],[Date]],"yyyy-mm-dd") -> 1_2010-02-12 | O3: =VLOOKUP($N3,Features!A3:N145,4,FALSE) -> 38.51 | P3: =VLOOKUP($N3,Features!A3:N145,11,FALSE) -> 211.24217 | Q3: =VLOOKUP($N3,Features!A3:N145,14,FALSE) -> 0 | R3: =IF(Table2[[#This Row],[3_Week_Forecast]]<Table2[[#This Row],[Weekly_Sales]], "Underforecast", "Overforecast") -> Underforecast
A4: 1 | B4: 1 | C4: 40228 | D4: 41595.55 | E4: FALSE | F4: =YEAR(Table2[[#This Row],[Date]]) -> 2010 | G4: =TEXT(Table2[[#This Row],[Date]],"mmm") -> Feb | H4: =TEXT(Table2[[#This Row],[Date]],"yyyy-mm") -> 2010-02 | I4: =WEEKNUM(Table2[[#This Row],[Date]]) -> 8 | J4: =Table2[[#This Row],[Weekly_Sales]]*2 -> 83191.1 | N4: =Table2[[#This Row],[Store]] & "_" & TEXT(Table2[[#This Row],[Date]],"yyyy-mm-dd") -> 1_2010-02-19 | O4: =VLOOKUP($N4,Features!A4:N146,4,FALSE) -> 39.93 | P4: =VLOOKUP($N4,Features!A4:N146,11,FALSE) -> 211.28914 | Q4: =VLOOKUP($N4,Features!A4:N146,14,FALSE) -> 0 | R4: =IF(Table2[[#This Row],[3_Week_Forecast]]<Table2[[#This Row],[Weekly_Sales]], "Underforecast", "Overforecast") -> Underforecast | T4: 1️⃣ Total Weekly Sales | V4: Month_Year | W4: Sum of Weekly_Sales | Y4: Shows long-term demand trend. | AF4: Month | AG4: Average of Weekly_Sales | AI4: Shows seasonal patterns.
A5: 1 | B5: 1 | C5: 40235 | D5: 19403.54 | E5: FALSE | F5: =YEAR(Table2[[#This Row],[Date]]) -> 2010 | G5: =TEXT(Table2[[#This Row],[Date]],"mmm") -> Feb | H5: =TEXT(Table2[[#This Row],[Date]],"yyyy-mm") -> 2010-02 | I5: =WEEKNUM(Table2[[#This Row],[Date]]) -> 9 | J5: =Table2[[#This Row],[Weekly_Sales]]*2 -> 38807.08 | K5: =AVERAGE(D2:D4) -> 37519.847 | L5: =Table2[[#This Row],[Weekly_Sales]]-Table2[[#This Row],[3_Week_Forecast]] -> -18116.307 | M5: =ABS(Table2[[#This Row],[Forecast Error]]/Table2[[#This Row],[Weekly_Sales]])*100 -> 93.365987 | N5: =Table2[[#This Row],[Store]] & "_" & TEXT(Table2[[#This Row],[Date]],"yyyy-mm-dd") -> 1_2010-02-26 | O5: =VLOOKUP($N5,Features!A5:N147,4,FALSE) -> 46.63 | P5: =VLOOKUP($N5,Features!A5:N147,11,FALSE) -> 211.31964 | Q5: =VLOOKUP($N5,Features!A5:N147,14,FALSE) -> 0 | R5: =IF(Table2[[#This Row],[3_Week_Forecast]]<Table2[[#This Row],[Weekly_Sales]], "Underforecast", "Overforecast") -> Overforecast | T5: =SUM(Weekly_Sales) -> 3219405.2 | V5: 2010-02 | W5: 131963.08 | AF5: Jan | AG5: 17418.993
A6: 1 | B6: 1 | C6: 40242 | D6: 21827.9 | E6: FALSE | F6: =YEAR(Table2[[#This Row],[Date]]) -> 2010 | G6: =TEXT(Table2[[#This Row],[Date]],"mmm") -> Mar | H6: =TEXT(Table2[[#This Row],[Date]],"yyyy-mm") -> 2010-03 | I6: =WEEKNUM(Table2[[#This Row],[Date]]) -> 10 | J6: =Table2[[#This Row],[Weekly_Sales]]*2 -> 43655.8 | K6: =AVERAGE(D3:D5) -> 35679.527 | L6: =Table2[[#This Row],[Weekly_Sales]]-Table2[[#This Row],[3_Week_Forecast]] -> -13851.627 | M6: =ABS(Table2[[#This Row],[Forecast Error]]/Table2[[#This Row],[Weekly_Sales]])*100 -> 63.458357 | N6: =Table2[[#This Row],[Store]] & "_" & TEXT(Table2[[#This Row],[Date]],"yyyy-mm-dd") -> 1_2010-03-05 | O6: =VLOOKUP($N6,Features!A6:N148,4,FALSE) -> 46.5 | P6: =VLOOKUP($N6,Features!A6:N148,11,FALSE) -> 211.35014 | Q6: =VLOOKUP($N6,Features!A6:N148,14,FALSE) -> 0 | R6: =IF(Table2[[#This Row],[3_Week_Forecast]]<Table2[[#This Row],[Weekly_Sales]], "Underforecast", "Overforecast") -> Overforecast | V6: 2010-03 | W6: 91237.14 | AF6: Feb | AG6: 32700.751
A7: 1 | B7: 1 | C7: 40249 | D7: 21043.39 | E7: FALSE | F7: =YEAR(Table2[[#This Row],[Date]]) -> 2010 | G7: =TEXT(Table2[[#This Row],[Date]],"mmm") -> Mar | H7: =TEXT(Table2[[#This Row],[Date]],"yyyy-mm") -> 2010-03 | I7: =WEEKNUM(Table2[[#This Row],[Date]]) -> 11 | J7: =Table2[[#This Row],[Weekly_Sales]]*2 -> 42086.78 | K7: =AVERAGE(D4:D6) -> 27608.997 | L7: =Table2[[#This Row],[Weekly_Sales]]-Table2[[#This Row],[3_Week_Forecast]] -> -6565.6067 | M7: =ABS(Table2[[#This Row],[Forecast Error]]/Table2[[#This Row],[Weekly_Sales]])*100 -> 31.200328 | N7: =Table2[[#This Row],[Store]] & "_" & TEXT(Table2[[#This Row],[Date]],"yyyy-mm-dd") -> 1_2010-03-12 | O7: =VLOOKUP($N7,Features!A7:N149,4,FALSE) -> 57.79 | P7: =VLOOKUP($N7,Features!A7:N149,11,FALSE) -> 211.38064 | Q7: =VLOOKUP($N7,Features!A7:N149,14,FALSE) -> 0 | R7: =IF(Table2[[#This Row],[3_Week_Forecast]]<Table2[[#This Row],[Weekly_Sales]], "Underforecast", "Overforecast") -> Overforecast | T7: 2️⃣ Average Weekly Sales | V7: 2010-04 | W7: 150516.76 | AF7: Mar | AG7: 22210.848
A8: 1 | B8: 1 | C8: 40256 | D8: 22136.64 | E8: FALSE | F8: =YEAR(Table2[[#This Row],[Date]]) -> 2010 | G8: =TEXT(Table2[[#This Row],[Date]],"mmm") -> Mar | H8: =TEXT(Table2[[#This Row],[Date]],"yyyy-mm") -> 2010-03 | I8: =WEEKNUM(Table2[[#This Row],[Date]]) -> 12 | J8: =Table2[[#This Row],[Weekly_Sales]]*2 -> 44273.28 | K8: =AVERAGE(D5:D7) -> 20758.277 | L8: =Table2[[#This Row],[Weekly_Sales]]-Table2[[#This Row],[3_Week_Forecast]] -> 1378.3633 | M8: =ABS(Table2[[#This Row],[Forecast Error]]/Table2[[#This Row],[Weekly_Sales]])*100 -> 6.2266149 | N8: =Table2[[#This Row],[Store]] & "_" & TEXT(Table2[[#This Row],[Date]],"yyyy-mm-dd") -> 1_2010-03-19 | O8: =VLOOKUP($N8,Features!A8:N150,4,FALSE) -> 54.58 | P8: =VLOOKUP($N8,Features!A8:N150,11,FALSE) -> 211.21563 | Q8: =VLOOKUP($N8,Features!A8:N150,14,FALSE) -> 0 | R8: =IF(Table2[[#This Row],[3_Week_Forecast]]<Table2[[#This Row],[Weekly_Sales]], "Underforecast", "Overforecast") -> Underforecast | T8: =AVERAGE(Weekly_Sales) -> 22513.323 | V8: 2010-05 | W8: 66694.15 | AF8: Apr | AG8: 31512.416
A9: 1 | B9: 1 | C9: 40263 | D9: 26229.21 | E9: FALSE | F9: =YEAR(Table2[[#This Row],[Date]]) -> 2010 | G9: =TEXT(Table2[[#This Row],[Date]],"mmm") -> Mar | H9: =TEXT(Table2[[#This Row],[Date]],"yyyy-mm") -> 2010-03 | I9: =WEEKNUM(Table2[[#This Row],[Date]]) -> 13 | J9: =Table2[[#This Row],[Weekly_Sales]]*2 -> 52458.42 | K9: =AVERAGE(D6:D8) -> 21669.31 | L9: =Table2[[#This Row],[Weekly_Sales]]-Table2[[#This Row],[3_Week_Forecast]] -> 4559.9 | M9: =ABS(Table2[[#This Row],[Forecast Error]]/Table2[[#This Row],[Weekly_Sales]])*100 -> 17.384816 | N9: =Table2[[#This Row],[Store]] & "_" & TEXT(Table2[[#This Row],[Date]],"yyyy-mm-dd") -> 1_2010-03-26 | O9: =VLOOKUP($N9,Features!A9:N151,4,FALSE) -> 51.45 | P9: =VLOOKUP($N9,Features!A9:N151,11,FALSE) -> 211.01804 | Q9: =VLOOKUP($N9,Features!A9:N151,14,FALSE) -> 0 | R9: =IF(Table2[[#This Row],[3_Week_Forecast]]<Table2[[#This Row],[Weekly_Sales]], "Underforecast", "Overforecast") -> Underforecast | V9: 2010-06 | W9: 66740.7 | AF9: May | AG9: 17144.904
A10: 1 | B10: 1 | C10: 40270 | D10: 57258.43 | E10: FALSE | F10: =YEAR(Table2[[#This Row],[Date]]) -> 2010 | G10: =TEXT(Table2[[#This Row],[Date]],"mmm") -> Apr | H10: =TEXT(Table2[[#This Row],[Date]],"yyyy-mm") -> 2010-04 | I10: =WEEKNUM(Table2[[#This Row],[Date]]) -> 14 | J10: =Table2[[#This Row],[Weekly_Sales]]*2 -> 114516.86 | K10: =AVERAGE(D7:D9) -> 23136.413 | L10: =Table2[[#This Row],[Weekly_Sales]]-Table2[[#This Row],[3_Week_Forecast]] -> 34122.017 | M10: =ABS(Table2[[#This Row],[Forecast Error]]/Table2[[#This Row],[Weekly_Sales]])*100 -> 59.593001 | N10: =Table2[[#This Row],[Store]] & "_" & TEXT(Table2[[#This Row],[Date]],"yyyy-mm-dd") -> 1_2010-04-02 | O10: =VLOOKUP($N10,Features!A10:N152,4,FALSE) -> 62.27 | P10: =VLOOKUP($N10,Features!A10:N152,11,FALSE) -> 210.82045 | Q10: =VLOOKUP($N10,Features!A10:N152,14,FALSE) -> 0 | R10: =IF(Table2[[#This Row],[3_Week_Forecast]]<Table2[[#This Row],[Weekly_Sales]], "Underforecast", "Overforecast") -> Underforecast | T10: 3️⃣ Average Inventory | V10: 2010-07 | W10: 81915.01 | AF10: Jun | AG10: 16412.755
A11: 1 | B11: 1 | C11: 40277 | D11: 42960.91 | E11: FALSE | F11: =YEAR(Table2[[#This Row],[Date]]) -> 2010 | G11: =TEXT(Table2[[#This Row],[Date]],"mmm") -> Apr | H11: =TEXT(Table2[[#This Row],[Date]],"yyyy-mm") -> 2010-04 | I11: =WEEKNUM(Table2[[#This Row],[Date]]) -> 15 | J11: =Table2[[#This Row],[Weekly_Sales]]*2 -> 85921.82 | K11: =AVERAGE(D8:D10) -> 35208.093 | L11: =Table2[[#This Row],[Weekly_Sales]]-Table2[[#This Row],[3_Week_Forecast]] -> 7752.8167 | M11: =ABS(Table2[[#This Row],[Forecast Error]]/Table2[[#This Row],[Weekly_Sales]])*100 -> 18.046211 | N11: =Table2[[#This Row],[Store]] & "_" & TEXT(Table2[[#This Row],[Date]],"yyyy-mm-dd") -> 1_2010-04-09 | O11: =VLOOKUP($N11,Features!A11:N153,4,FALSE) -> 65.86 | P11: =VLOOKUP($N11,Features!A11:N153,11,FALSE) -> 210.62286 | Q11: =VLOOKUP($N11,Features!A11:N153,14,FALSE) -> 0 | R11: =IF(Table2[[#This Row],[3_Week_Forecast]]<Table2[[#This Row],[Weekly_Sales]], "Underforecast", "Overforecast") -> Underforecast | T11: =AVERAGE(Inventory) -> 45026.646 | V11: 2010-08 | W11: 64578.81 | AF11: Jul | AG11: 16231.431
A12: 1 | B12: 1 | C12: 40284 | D12: 17596.96 | E12: FALSE | F12: =YEAR(Table2[[#This Row],[Date]]) -> 2010 | G12: =TEXT(Table2[[#This Row],[Date]],"mmm") -> Apr | H12: =TEXT(Table2[[#This Row],[Date]],"yyyy-mm") -> 2010-04 | I12: =WEEKNUM(Table2[[#This Row],[Date]]) -> 16 | J12: =Table2[[#This Row],[Weekly_Sales]]*2 -> 35193.92 | K12: =AVERAGE(D9:D11) -> 42149.517 | L12: =Table2[[#This Row],[Weekly_Sales]]-Table2[[#This Row],[3_Week_Forecast]] -> -24552.557 | M12: =ABS(Table2[[#This Row],[Forecast Error]]/Table2[[#This Row],[Weekly_Sales]])*100 -> 139.52726 | N12: =Table2[[#This Row],[Store]] & "_" & TEXT(Table2[[#This Row],[Date]],"yyyy-mm-dd") -> 1_2010-04-16 | O12: =VLOOKUP($N12,Features!A12:N154,4,FALSE) -> 66.32 | P12: =VLOOKUP($N12,Features!A12:N154,11,FALSE) -> 210.4887 | Q12: =VLOOKUP($N12,Features!A12:N154,14,FALSE) -> 0 | R12: =IF(Table2[[#This Row],[3_Week_Forecast]]<Table2[[#This Row],[Weekly_Sales]], "Underforecast", "Overforecast") -> Overforecast | V12: 2010-09 | W12: 71913.27 | AF12: Aug | AG12: 15898.948
A13: 1 | B13: 1 | C13: 40291 | D13: 16145.35 | E13: FALSE | F13: =YEAR(Table2[[#This Row],[Date]]) -> 2010 | G13: =TEXT(Table2[[#This Row],[Date]],"mmm") -> Apr | H13: =TEXT(Table2[[#This Row],[Date]],"yyyy-mm") -> 2010-04 | I13: =WEEKNUM(Table2[[#This Row],[Date]]) -> 17 | J13: =Table2[[#This Row],[Weekly_Sales]]*2 -> 32290.7 | K13: =AVERAGE(D10:D12) -> 39272.1 | L13: =Table2[[#This Row],[Weekly_Sales]]-Table2[[#This Row],[3_Week_Forecast]] -> -23126.75 | M13: =ABS(Table2[[#This Row],[Forecast Error]]/Table2[[#This Row],[Weekly_Sales]])*100 -> 143.24093 | N13: =Table2[[#This Row],[Store]] & "_" & TEXT(Table2[[#This Row],[Date]],"yyyy-mm-dd") -> 1_2010-04-23 | O13: =VLOOKUP($N13,Features!A13:N155,4,FALSE) -> 64.84 | P13: =VLOOKUP($N13,Features!A13:N155,11,FALSE) -> 210.43912 | Q13: =VLOOKUP($N13,Features!A13:N155,14,FALSE) -> 0 | R13: =IF(Table2[[#This Row],[3_Week_Forecast]]<Table2[[#This Row],[Weekly_Sales]], "Underforecast", "Overforecast") -> Overforecast | T13: 4️⃣ Inventory Turnover | V13: 2010-10 | W13: 134644.53 | AF13: Sep | AG13: 18139.045
A14: 1 | B14: 1 | C14: 40298 | D14: 16555.11 | E14: FALSE | F14: =YEAR(Table2[[#This Row],[Date]]) -> 2010 | G14: =TEXT(Table2[[#This Row],[Date]],"mmm") -> Apr | H14: =TEXT(Table2[[#This Row],[Date]],"yyyy-mm") -> 2010-04 | I14: =WEEKNUM(Table2[[#This Row],[Date]]) -> 18 | J14: =Table2[[#This Row],[Weekly_Sales]]*2 -> 33110.22 | K14: =AVERAGE(D11:D13) -> 25567.74 | L14: =Table2[[#This Row],[Weekly_Sales]]-Table2[[#This Row],[3_Week_Forecast]] -> -9012.63 | M14: =ABS(Table2[[#This Row],[Forecast Error]]/Table2[[#This Row],[Weekly_Sales]])*100 -> 54.44017 | N14: =Table2[[#This Row],[Store]] & "_" & TEXT(Table2[[#This Row],[Date]],"yyyy-mm-dd") -> 1_2010-04-30 | O14: =VLOOKUP($N14,Features!A14:N156,4,FALSE) -> 67.41 | P14: =VLOOKUP($N14,Features!A14:N156,11,FALSE) -> 210.38955 | Q14: =VLOOKUP($N14,Features!A14:N156,14,FALSE) -> 0 | R14: =IF(Table2[[#This Row],[3_Week_Forecast]]<Table2[[#This Row],[Weekly_Sales]], "Underforecast", "Overforecast") -> Overforecast | T14: =T5/T11 -> 71.5 | V14: 2010-11 | W14: 92161.4 | AF14: Oct | AG14: 25361.225
A15: 1 | B15: 1 | C15: 40305 | D15: 17413.94 | E15: FALSE | F15: =YEAR(Table2[[#This Row],[Date]]) -> 2010 | G15: =TEXT(Table2[[#This Row],[Date]],"mmm") -> May | H15: =TEXT(Table2[[#This Row],[Date]],"yyyy-mm") -> 2010-05 | I15: =WEEKNUM(Table2[[#This Row],[Date]]) -> 19 | J15: =Table2[[#This Row],[Weekly_Sales]]*2 -> 34827.88 | K15: =AVERAGE(D12:D14) -> 16765.807 | L15: =Table2[[#This Row],[Weekly_Sales]]-Table2[[#This Row],[3_Week_Forecast]] -> 648.13333 | M15: =ABS(Table2[[#This Row],[Forecast Error]]/Table2[[#This Row],[Weekly_Sales]])*100 -> 3.7219224 | N15: =Table2[[#This Row],[Store]] & "_" & TEXT(Table2[[#This Row],[Date]],"yyyy-mm-dd") -> 1_2010-05-07 | O15: =VLOOKUP($N15,Features!A15:N157,4,FALSE) -> 72.55 | P15: =VLOOKUP($N15,Features!A15:N157,11,FALSE) -> 210.33997 | Q15: =VLOOKUP($N15,Features!A15:N157,14,FALSE) -> 0 | R15: =IF(Table2[[#This Row],[3_Week_Forecast]]<Table2[[#This Row],[Weekly_Sales]], "Underforecast", "Overforecast") -> Underforecast | V15: 2010-12 | W15: 173983.88 | AF15: Nov | AG15: 23837.364
A16: 1 | B16: 1 | C16: 40312 | D16: 18926.74 | E16: FALSE | F16: =YEAR(Table2[[#This Row],[Date]]) -> 2010 | G16: =TEXT(Table2[[#This Row],[Date]],"mmm") -> May | H16: =TEXT(Table2[[#This Row],[Date]],"yyyy-mm") -> 2010-05 | I16: =WEEKNUM(Table2[[#This Row],[Date]]) -> 20 | J16: =Table2[[#This Row],[Weekly_Sales]]*2 -> 37853.48 | K16: =AVERAGE(D13:D15) -> 16704.8 | L16: =Table2[[#This Row],[Weekly_Sales]]-Table2[[#This Row],[3_Week_Forecast]] -> 2221.94 | M16: =ABS(Table2[[#This Row],[Forecast Error]]/Table2[[#This Row],[Weekly_Sales]])*100 -> 11.739687 | N16: =Table2[[#This Row],[Store]] & "_" & TEXT(Table2[[#This Row],[Date]],"yyyy-mm-dd") -> 1_2010-05-14 | O16: =VLOOKUP($N16,Features!A16:N158,4,FALSE) -> 74.78 | P16: =VLOOKUP($N16,Features!A16:N158,11,FALSE) -> 210.33743 | Q16: =VLOOKUP($N16,Features!A16:N158,14,FALSE) -> 0 | R16: =IF(Table2[[#This Row],[3_Week_Forecast]]<Table2[[#This Row],[Weekly_Sales]], "Underforecast", "Overforecast") -> Underforecast | T16: 5️⃣ Annnual Inventory Turnover | V16: 2011-01 | W16: 69146.59 | AF16: Dec | AG16: 34849.595
A17: 1 | B17: 1 | C17: 40319 | D17: 14773.04 | E17: FALSE | F17: =YEAR(Table2[[#This Row],[Date]]) -> 2010 | G17: =TEXT(Table2[[#This Row],[Date]],"mmm") -> May | H17: =TEXT(Table2[[#This Row],[Date]],"yyyy-mm") -> 2010-05 | I17: =WEEKNUM(Table2[[#This Row],[Date]]) -> 21 | J17: =Table2[[#This Row],[Weekly_Sales]]*2 -> 29546.08 | K17: =AVERAGE(D14:D16) -> 17631.93 | L17: =Table2[[#This Row],[Weekly_Sales]]-Table2[[#This Row],[3_Week_Forecast]] -> -2858.89 | M17: =ABS(Table2[[#This Row],[Forecast Error]]/Table2[[#This Row],[Weekly_Sales]])*100 -> 19.352076 | N17: =Table2[[#This Row],[Store]] & "_" & TEXT(Table2[[#This Row],[Date]],"yyyy-mm-dd") -> 1_2010-05-21 | O17: =VLOOKUP($N17,Features!A17:N159,4,FALSE) -> 76.44 | P17: =VLOOKUP($N17,Features!A17:N159,11,FALSE) -> 210.61709 | Q17: =VLOOKUP($N17,Features!A17:N159,14,FALSE) -> 0 | R17: =IF(Table2[[#This Row],[3_Week_Forecast]]<Table2[[#This Row],[Weekly_Sales]], "Underforecast", "Overforecast") -> Overforecast | T17: =T14/((MAX(C2:C144)-MIN(C2:C144))/365) -> 26.25503 | V17: 2011-02 | W17: 125762.63 | AF17: Grand Total | AG17: 22513.323
A18: 1 | B18: 1 | C18: 40326 | D18: 15580.43 | E18: FALSE | F18: =YEAR(Table2[[#This Row],[Date]]) -> 2010 | G18: =TEXT(Table2[[#This Row],[Date]],"mmm") -> May | H18: =TEXT(Table2[[#This Row],[Date]],"yyyy-mm") -> 2010-05 | I18: =WEEKNUM(Table2[[#This Row],[Date]]) -> 22 | J18: =Table2[[#This Row],[Weekly_Sales]]*2 -> 31160.86 | K18: =AVERAGE(D15:D17) -> 17037.907 | L18: =Table2[[#This Row],[Weekly_Sales]]-Table2[[#This Row],[3_Week_Forecast]] -> -1457.4767 | M18: =ABS(Table2[[#This Row],[Forecast Error]]/Table2[[#This Row],[Weekly_Sales]])*100 -> 9.3545343 | N18: =Table2[[#This Row],[Store]] & "_" & TEXT(Table2[[#This Row],[Date]],"yyyy-mm-dd") -> 1_2010-05-28 | O18: =VLOOKUP($N18,Features!A18:N160,4,FALSE) -> 80.44 | P18: =VLOOKUP($N18,Features!A18:N160,11,FALSE) -> 210.89676 | Q18: =VLOOKUP($N18,Features!A18:N160,14,FALSE) -> 0 | R18: =IF(Table2[[#This Row],[3_Week_Forecast]]<Table2[[#This Row],[Weekly_Sales]], "Underforecast", "Overforecast") -> Overforecast | V18: 2011-03 | W18: 82823.34
A19: 1 | B19: 1 | C19: 40333 | D19: 17558.09 | E19: FALSE | F19: =YEAR(Table2[[#This Row],[Date]]) -> 2010 | G19: =TEXT(Table2[[#This Row],[Date]],"mmm") -> Jun | H19: =TEXT(Table2[[#This Row],[Date]],"yyyy-mm") -> 2010-06 | I19: =WEEKNUM(Table2[[#This Row],[Date]]) -> 23 | J19: =Table2[[#This Row],[Weekly_Sales]]*2 -> 35116.18 | K19: =AVERAGE(D16:D18) -> 16426.737 | L19: =Table2[[#This Row],[Weekly_Sales]]-Table2[[#This Row],[3_Week_Forecast]] -> 1131.3533 | M19: =ABS(Table2[[#This Row],[Forecast Error]]/Table2[[#This Row],[Weekly_Sales]])*100 -> 6.4434875 | N19: =Table2[[#This Row],[Store]] & "_" & TEXT(Table2[[#This Row],[Date]],"yyyy-mm-dd") -> 1_2010-06-04 | O19: =VLOOKUP($N19,Features!A19:N161,4,FALSE) -> 80.69 | P19: =VLOOKUP($N19,Features!A19:N161,11,FALSE) -> 211.17643 | Q19: =VLOOKUP($N19,Features!A19:N161,14,FALSE) -> 0 | R19: =IF(Table2[[#This Row],[3_Week_Forecast]]<Table2[[#This Row],[Weekly_Sales]], "Underforecast", "Overforecast") -> Underforecast | T19: 6️⃣ Reorder Point (ROP) | V19: 2011-04 | W19: 165056.95
A20: 1 | B20: 1 | C20: 40340 | D20: 16637.62 | E20: FALSE | F20: =YEAR(Table2[[#This Row],[Date]]) -> 2010 | G20: =TEXT(Table2[[#This Row],[Date]],"mmm") -> Jun | H20: =TEXT(Table2[[#This Row],[Date]],"yyyy-mm") -> 2010-06 | I20: =WEEKNUM(Table2[[#This Row],[Date]]) -> 24 | J20: =Table2[[#This Row],[Weekly_Sales]]*2 -> 33275.24 | K20: =AVERAGE(D17:D19) -> 15970.52 | L20: =Table2[[#This Row],[Weekly_Sales]]-Table2[[#This Row],[3_Week_Forecast]] -> 667.1 | M20: =ABS(Table2[[#This Row],[Forecast Error]]/Table2[[#This Row],[Weekly_Sales]])*100 -> 4.0095879 | N20: =Table2[[#This Row],[Store]] & "_" & TEXT(Table2[[#This Row],[Date]],"yyyy-mm-dd") -> 1_2010-06-11 | O20: =VLOOKUP($N20,Features!A20:N162,4,FALSE) -> 80.43 | P20: =VLOOKUP($N20,Features!A20:N162,11,FALSE) -> 211.4561 | Q20: =VLOOKUP($N20,Features!A20:N162,14,FALSE) -> 0 | R20: =IF(Table2[[#This Row],[3_Week_Forecast]]<Table2[[#This Row],[Weekly_Sales]], "Underforecast", "Overforecast") -> Underforecast | T20: =T8*2 -> 45026.646 | V20: 2011-05 | W20: 68251.72
A21: 1 | B21: 1 | C21: 40347 | D21: 16216.27 | E21: FALSE | F21: =YEAR(Table2[[#This Row],[Date]]) -> 2010 | G21: =TEXT(Table2[[#This Row],[Date]],"mmm") -> Jun | H21: =TEXT(Table2[[#This Row],[Date]],"yyyy-mm") -> 2010-06 | I21: =WEEKNUM(Table2[[#This Row],[Date]]) -> 25 | J21: =Table2[[#This Row],[Weekly_Sales]]*2 -> 32432.54 | K21: =AVERAGE(D18:D20) -> 16592.047 | L21: =Table2[[#This Row],[Weekly_Sales]]-Table2[[#This Row],[3_Week_Forecast]] -> -375.77667 | M21: =ABS(Table2[[#This Row],[Forecast Error]]/Table2[[#This Row],[Weekly_Sales]])*100 -> 2.3172818 | N21: =Table2[[#This Row],[Store]] & "_" & TEXT(Table2[[#This Row],[Date]],"yyyy-mm-dd") -> 1_2010-06-18 | O21: =VLOOKUP($N21,Features!A21:N163,4,FALSE) -> 84.11 | P21: =VLOOKUP($N21,Features!A21:N163,11,FALSE) -> 211.45377 | Q21: =VLOOKUP($N21,Features!A21:N163,14,FALSE) -> 0 | R21: =IF(Table2[[#This Row],[3_Week_Forecast]]<Table2[[#This Row],[Weekly_Sales]], "Underforecast", "Overforecast") -> Overforecast | V21: 2011-06 | W21: 62978.57
A22: 1 | B22: 1 | C22: 40354 | D22: 16328.72 | E22: FALSE | F22: =YEAR(Table2[[#This Row],[Date]]) -> 2010 | G22: =TEXT(Table2[[#This Row],[Date]],"mmm") -> Jun | H22: =TEXT(Table2[[#This Row],[Date]],"yyyy-mm") -> 2010-06 | I22: =WEEKNUM(Table2[[#This Row],[Date]]) -> 26 | J22: =Table2[[#This Row],[Weekly_Sales]]*2 -> 32657.44 | K22: =AVERAGE(D19:D21) -> 16803.993 | L22: =Table2[[#This Row],[Weekly_Sales]]-Table2[[#This Row],[3_Week_Forecast]] -> -475.27333 | M22: =ABS(Table2[[#This Row],[Forecast Error]]/Table2[[#This Row],[Weekly_Sales]])*100 -> 2.9106588 | N22: =Table2[[#This Row],[Store]] & "_" & TEXT(Table2[[#This Row],[Date]],"yyyy-mm-dd") -> 1_2010-06-25 | O22: =VLOOKUP($N22,Features!A22:N164,4,FALSE) -> 84.34 | P22: =VLOOKUP($N22,Features!A22:N164,11,FALSE) -> 211.33865 | Q22: =VLOOKUP($N22,Features!A22:N164,14,FALSE) -> 0 | R22: =IF(Table2[[#This Row],[3_Week_Forecast]]<Table2[[#This Row],[Weekly_Sales]], "Underforecast", "Overforecast") -> Overforecast | T22: 7️⃣ Average APE | V22: 2011-07 | W22: 78856.23
A23: 1 | B23: 1 | C23: 40361 | D23: 16333.14 | E23: FALSE | F23: =YEAR(Table2[[#This Row],[Date]]) -> 2010 | G23: =TEXT(Table2[[#This Row],[Date]],"mmm") -> Jul | H23: =TEXT(Table2[[#This Row],[Date]],"yyyy-mm") -> 2010-07 | I23: =WEEKNUM(Table2[[#This Row],[Date]]) -> 27 | J23: =Table2[[#This Row],[Weekly_Sales]]*2 -> 32666.28 | K23: =AVERAGE(D20:D22) -> 16394.203 | L23: =Table2[[#This Row],[Weekly_Sales]]-Table2[[#This Row],[3_Week_Forecast]] -> -61.063333 | M23: =ABS(Table2[[#This Row],[Forecast Error]]/Table2[[#This Row],[Weekly_Sales]])*100 -> 0.37386157 | N23: =Table2[[#This Row],[Store]] & "_" & TEXT(Table2[[#This Row],[Date]],"yyyy-mm-dd") -> 1_2010-07-02 | O23: =VLOOKUP($N23,Features!A23:N165,4,FALSE) -> 80.91 | P23: =VLOOKUP($N23,Features!A23:N165,11,FALSE) -> 211.22353 | Q23: =VLOOKUP($N23,Features!A23:N165,14,FALSE) -> 0 | R23: =IF(Table2[[#This Row],[3_Week_Forecast]]<Table2[[#This Row],[Weekly_Sales]], "Underforecast", "Overforecast") -> Overforecast | T23: =AVERAGE(M5:M144) -> 27.750657 | V23: 2011-08 | W23: 59061.95
A24: 1 | B24: 1 | C24: 40368 | D24: 17688.76 | E24: FALSE | F24: =YEAR(Table2[[#This Row],[Date]]) -> 2010 | G24: =TEXT(Table2[[#This Row],[Date]],"mmm") -> Jul | H24: =TEXT(Table2[[#This Row],[Date]],"yyyy-mm") -> 2010-07 | I24: =WEEKNUM(Table2[[#This Row],[Date]]) -> 28 | J24: =Table2[[#This Row],[Weekly_Sales]]*2 -> 35377.52 | K24: =AVERAGE(D21:D23) -> 16292.71 | L24: =Table2[[#This Row],[Weekly_Sales]]-Table2[[#This Row],[3_Week_Forecast]] -> 1396.05 | M24: =ABS(Table2[[#This Row],[Forecast Error]]/Table2[[#This Row],[Weekly_Sales]])*100 -> 7.8923 | N24: =Table2[[#This Row],[Store]] & "_" & TEXT(Table2[[#This Row],[Date]],"yyyy-mm-dd") -> 1_2010-07-09 | O24: =VLOOKUP($N24,Features!A24:N166,4,FALSE) -> 80.48 | P24: =VLOOKUP($N24,Features!A24:N166,11,FALSE) -> 211.10841 | Q24: =VLOOKUP($N24,Features!A24:N166,14,FALSE) -> 0 | R24: =IF(Table2[[#This Row],[3_Week_Forecast]]<Table2[[#This Row],[Weekly_Sales]], "Underforecast", "Overforecast") -> Underforecast | V24: 2011-09 | W24: 87756.41
A25: 1 | B25: 1 | C25: 40375 | D25: 17150.84 | E25: FALSE | F25: =YEAR(Table2[[#This Row],[Date]]) -> 2010 | G25: =TEXT(Table2[[#This Row],[Date]],"mmm") -> Jul | H25: =TEXT(Table2[[#This Row],[Date]],"yyyy-mm") -> 2010-07 | I25: =WEEKNUM(Table2[[#This Row],[Date]]) -> 29 | J25: =Table2[[#This Row],[Weekly_Sales]]*2 -> 34301.68 | K25: =AVERAGE(D22:D24) -> 16783.54 | L25: =Table2[[#This Row],[Weekly_Sales]]-Table2[[#This Row],[3_Week_Forecast]] -> 367.3 | M25: =ABS(Table2[[#This Row],[Forecast Error]]/Table2[[#This Row],[Weekly_Sales]])*100 -> 2.1415861 | N25: =Table2[[#This Row],[Store]] & "_" & TEXT(Table2[[#This Row],[Date]],"yyyy-mm-dd") -> 1_2010-07-16 | O25: =VLOOKUP($N25,Features!A25:N167,4,FALSE) -> 83.15 | P25: =VLOOKUP($N25,Features!A25:N167,11,FALSE) -> 211.10039 | Q25: =VLOOKUP($N25,Features!A25:N167,14,FALSE) -> 0 | R25: =IF(Table2[[#This Row],[3_Week_Forecast]]<Table2[[#This Row],[Weekly_Sales]], "Underforecast", "Overforecast") -> Underforecast | V25: 2011-10 | W25: 98806.83
A26: 1 | B26: 1 | C26: 40382 | D26: 15360.45 | E26: FALSE | F26: =YEAR(Table2[[#This Row],[Date]]) -> 2010 | G26: =TEXT(Table2[[#This Row],[Date]],"mmm") -> Jul | H26: =TEXT(Table2[[#This Row],[Date]],"yyyy-mm") -> 2010-07 | I26: =WEEKNUM(Table2[[#This Row],[Date]]) -> 30 | J26: =Table2[[#This Row],[Weekly_Sales]]*2 -> 30720.9 | K26: =AVERAGE(D23:D25) -> 17057.58 | L26: =Table2[[#This Row],[Weekly_Sales]]-Table2[[#This Row],[3_Week_Forecast]] -> -1697.13 | M26: =ABS(Table2[[#This Row],[Forecast Error]]/Table2[[#This Row],[Weekly_Sales]])*100 -> 11.0487 | N26: =Table2[[#This Row],[Store]] & "_" & TEXT(Table2[[#This Row],[Date]],"yyyy-mm-dd") -> 1_2010-07-23 | O26: =VLOOKUP($N26,Features!A26:N168,4,FALSE) -> 83.36 | P26: =VLOOKUP($N26,Features!A26:N168,11,FALSE) -> 211.23514 | Q26: =VLOOKUP($N26,Features!A26:N168,14,FALSE) -> 0 | R26: =IF(Table2[[#This Row],[3_Week_Forecast]]<Table2[[#This Row],[Weekly_Sales]], "Underforecast", "Overforecast") -> Overforecast | V26: 2011-11 | W26: 98537.51
A27: 1 | B27: 1 | C27: 40389 | D27: 15381.82 | E27: FALSE | F27: =YEAR(Table2[[#This Row],[Date]]) -> 2010 | G27: =TEXT(Table2[[#This Row],[Date]],"mmm") -> Jul | H27: =TEXT(Table2[[#This Row],[Date]],"yyyy-mm") -> 2010-07 | I27: =WEEKNUM(Table2[[#This Row],[Date]]) -> 31 | J27: =Table2[[#This Row],[Weekly_Sales]]*2 -> 30763.64 | K27: =AVERAGE(D24:D26) -> 16733.35 | L27: =Table2[[#This Row],[Weekly_Sales]]-Table2[[#This Row],[3_Week_Forecast]] -> -1351.53 | M27: =ABS(Table2[[#This Row],[Forecast Error]]/Table2[[#This Row],[Weekly_Sales]])*100 -> 8.7865415 | N27: =Table2[[#This Row],[Store]] & "_" & TEXT(Table2[[#This Row],[Date]],"yyyy-mm-dd") -> 1_2010-07-30 | O27: =VLOOKUP($N27,Features!A27:N169,4,FALSE) -> 81.84 | P27: =VLOOKUP($N27,Features!A27:N169,11,FALSE) -> 211.3699 | Q27: =VLOOKUP($N27,Features!A27:N169,14,FALSE) -> 0 | R27: =IF(Table2[[#This Row],[3_Week_Forecast]]<Table2[[#This Row],[Weekly_Sales]], "Underforecast", "Overforecast") -> Overforecast | V27: 2011-12 | W27: 174512.07
A28: 1 | B28: 1 | C28: 40396 | D28: 17508.41 | E28: FALSE | F28: =YEAR(Table2[[#This Row],[Date]]) -> 2010 | G28: =TEXT(Table2[[#This Row],[Date]],"mmm") -> Aug | H28: =TEXT(Table2[[#This Row],[Date]],"yyyy-mm") -> 2010-08 | I28: =WEEKNUM(Table2[[#This Row],[Date]]) -> 32 | J28: =Table2[[#This Row],[Weekly_Sales]]*2 -> 35016.82 | K28: =AVERAGE(D25:D27) -> 15964.37 | L28: =Table2[[#This Row],[Weekly_Sales]]-Table2[[#This Row],[3_Week_Forecast]] -> 1544.04 | M28: =ABS(Table2[[#This Row],[Forecast Error]]/Table2[[#This Row],[Weekly_Sales]])*100 -> 8.8188476 | N28: =Table2[[#This Row],[Store]] & "_" & TEXT(Table2[[#This Row],[Date]],"yyyy-mm-dd") -> 1_2010-08-06 | O28: =VLOOKUP($N28,Features!A28:N170,4,FALSE) -> 87.16 | P28: =VLOOKUP($N28,Features!A28:N170,11,FALSE) -> 211.50466 | Q28: =VLOOKUP($N28,Features!A28:N170,14,FALSE) -> 0 | R28: =IF(Table2[[#This Row],[3_Week_Forecast]]<Table2[[#This Row],[Weekly_Sales]], "Underforecast", "Overforecast") -> Underforecast | V28: 2012-01 | W28: 70205.35
A29: 1 | B29: 1 | C29: 40403 | D29: 15536.4 | E29: FALSE | F29: =YEAR(Table2[[#This Row],[Date]]) -> 2010 | G29: =TEXT(Table2[[#This Row],[Date]],"mmm") -> Aug | H29: =TEXT(Table2[[#This Row],[Date]],"yyyy-mm") -> 2010-08 | I29: =WEEKNUM(Table2[[#This Row],[Date]]) -> 33 | J29: =Table2[[#This Row],[Weekly_Sales]]*2 -> 31072.8 | K29: =AVERAGE(D26:D28) -> 16083.56 | L29: =Table2[[#This Row],[Weekly_Sales]]-Table2[[#This Row],[3_Week_Forecast]] -> -547.16 | M29: =ABS(Table2[[#This Row],[Forecast Error]]/Table2[[#This Row],[Weekly_Sales]])*100 -> 3.521794 | N29: =Table2[[#This Row],[Store]] & "_" & TEXT(Table2[[#This Row],[Date]],"yyyy-mm-dd") -> 1_2010-08-13 | O29: =VLOOKUP($N29,Features!A29:N171,4,FALSE) -> 87 | P29: =VLOOKUP($N29,Features!A29:N171,11,FALSE) -> 211.63942 | Q29: =VLOOKUP($N29,Features!A29:N171,14,FALSE) -> 0 | R29: =IF(Table2[[#This Row],[3_Week_Forecast]]<Table2[[#This Row],[Weekly_Sales]], "Underforecast", "Overforecast") -> Overforecast | V29: 2012-02 | W29: 134683.3
A30: 1 | B30: 1 | C30: 40410 | D30: 15740.13 | E30: FALSE | F30: =YEAR(Table2[[#This Row],[Date]]) -> 2010 | G30: =TEXT(Table2[[#This Row],[Date]],"mmm") -> Aug | H30: =TEXT(Table2[[#This Row],[Date]],"yyyy-mm") -> 2010-08 | I30: =WEEKNUM(Table2[[#This Row],[Date]]) -> 34 | J30: =Table2[[#This Row],[Weekly_Sales]]*2 -> 31480.26 | K30: =AVERAGE(D27:D29) -> 16142.21 | L30: =Table2[[#This Row],[Weekly_Sales]]-Table2[[#This Row],[3_Week_Forecast]] -> -402.08 | M30: =ABS(Table2[[#This Row],[Forecast Error]]/Table2[[#This Row],[Weekly_Sales]])*100 -> 2.5544897 | N30: =Table2[[#This Row],[Store]] & "_" & TEXT(Table2[[#This Row],[Date]],"yyyy-mm-dd") -> 1_2010-08-20 | O30: =VLOOKUP($N30,Features!A30:N172,4,FALSE) -> 86.65 | P30: =VLOOKUP($N30,Features!A30:N172,11,FALSE) -> 211.60336 | Q30: =VLOOKUP($N30,Features!A30:N172,14,FALSE) -> 0 | R30: =IF(Table2[[#This Row],[3_Week_Forecast]]<Table2[[#This Row],[Weekly_Sales]], "Underforecast", "Overforecast") -> Overforecast | V30: 2012-03 | W30: 114680.54
A31: 1 | B31: 1 | C31: 40417 | D31: 15793.87 | E31: FALSE | F31: =YEAR(Table2[[#This Row],[Date]]) -> 2010 | G31: =TEXT(Table2[[#This Row],[Date]],"mmm") -> Aug | H31: =TEXT(Table2[[#This Row],[Date]],"yyyy-mm") -> 2010-08 | I31: =WEEKNUM(Table2[[#This Row],[Date]]) -> 35 | J31: =Table2[[#This Row],[Weekly_Sales]]*2 -> 31587.74 | K31: =AVERAGE(D28:D30) -> 16261.647 | L31: =Table2[[#This Row],[Weekly_Sales]]-Table2[[#This Row],[3_Week_Forecast]] -> -467.77667 | M31: =ABS(Table2[[#This Row],[Forecast Error]]/Table2[[#This Row],[Weekly_Sales]])*100 -> 2.9617609 | N31: =Table2[[#This Row],[Store]] & "_" & TEXT(Table2[[#This Row],[Date]],"yyyy-mm-dd") -> 1_2010-08-27 | O31: =VLOOKUP($N31,Features!A31:N173,4,FALSE) -> 85.22 | P31: =VLOOKUP($N31,Features!A31:N173,11,FALSE) -> 211.56731 | Q31: =VLOOKUP($N31,Features!A31:N173,14,FALSE) -> 0 | R31: =IF(Table2[[#This Row],[3_Week_Forecast]]<Table2[[#This Row],[Weekly_Sales]], "Underforecast", "Overforecast") -> Overforecast | V31: 2012-04 | W31: 125600.12
A32: 1 | B32: 1 | C32: 40424 | D32: 16241.78 | E32: FALSE | F32: =YEAR(Table2[[#This Row],[Date]]) -> 2010 | G32: =TEXT(Table2[[#This Row],[Date]],"mmm") -> Sep | H32: =TEXT(Table2[[#This Row],[Date]],"yyyy-mm") -> 2010-09 | I32: =WEEKNUM(Table2[[#This Row],[Date]]) -> 36 | J32: =Table2[[#This Row],[Weekly_Sales]]*2 -> 32483.56 | K32: =AVERAGE(D29:D31) -> 15690.133 | L32: =Table2[[#This Row],[Weekly_Sales]]-Table2[[#This Row],[3_Week_Forecast]] -> 551.64667 | M32: =ABS(Table2[[#This Row],[Forecast Error]]/Table2[[#This Row],[Weekly_Sales]])*100 -> 3.3964668 | N32: =Table2[[#This Row],[Store]] & "_" & TEXT(Table2[[#This Row],[Date]],"yyyy-mm-dd") -> 1_2010-09-03 | O32: =VLOOKUP($N32,Features!A32:N174,4,FALSE) -> 81.21 | P32: =VLOOKUP($N32,Features!A32:N174,11,FALSE) -> 211.53125 | Q32: =VLOOKUP($N32,Features!A32:N174,14,FALSE) -> 0 | R32: =IF(Table2[[#This Row],[3_Week_Forecast]]<Table2[[#This Row],[Weekly_Sales]], "Underforecast", "Overforecast") -> Underforecast | V32: 2012-05 | W32: 70792.98
A33: 1 | B33: 1 | C33: 40431 | D33: 18194.74 | E33: TRUE | F33: =YEAR(Table2[[#This Row],[Date]]) -> 2010 | G33: =TEXT(Table2[[#This Row],[Date]],"mmm") -> Sep | H33: =TEXT(Table2[[#This Row],[Date]],"yyyy-mm") -> 2010-09 | I33: =WEEKNUM(Table2[[#This Row],[Date]]) -> 37 | J33: =Table2[[#This Row],[Weekly_Sales]]*2 -> 36389.48 | K33: =AVERAGE(D30:D32) -> 15925.26 | L33: =Table2[[#This Row],[Weekly_Sales]]-Table2[[#This Row],[3_Week_Forecast]] -> 2269.48 | M33: =ABS(Table2[[#This Row],[Forecast Error]]/Table2[[#This Row],[Weekly_Sales]])*100 -> 12.473275 | N33: =Table2[[#This Row],[Store]] & "_" & TEXT(Table2[[#This Row],[Date]],"yyyy-mm-dd") -> 1_2010-09-10 | O33: =VLOOKUP($N33,Features!A33:N175,4,FALSE) -> 78.69 | P33: =VLOOKUP($N33,Features!A33:N175,11,FALSE) -> 211.49519 | Q33: =VLOOKUP($N33,Features!A33:N175,14,FALSE) -> 0 | R33: =IF(Table2[[#This Row],[3_Week_Forecast]]<Table2[[#This Row],[Weekly_Sales]], "Underforecast", "Overforecast") -> Underforecast | V33: 2012-06 | W33: 83646.54
A34: 1 | B34: 1 | C34: 40438 | D34: 19354.23 | E34: FALSE | F34: =YEAR(Table2[[#This Row],[Date]]) -> 2010 | G34: =TEXT(Table2[[#This Row],[Date]],"mmm") -> Sep | H34: =TEXT(Table2[[#This Row],[Date]],"yyyy-mm") -> 2010-09 | I34: =WEEKNUM(Table2[[#This Row],[Date]]) -> 38 | J34: =Table2[[#This Row],[Weekly_Sales]]*2 -> 38708.46 | K34: =AVERAGE(D31:D33) -> 16743.463 | L34: =Table2[[#This Row],[Weekly_Sales]]-Table2[[#This Row],[3_Week_Forecast]] -> 2610.7667 | M34: =ABS(Table2[[#This Row],[Forecast Error]]/Table2[[#This Row],[Weekly_Sales]])*100 -> 13.489385 | N34: =Table2[[#This Row],[Store]] & "_" & TEXT(Table2[[#This Row],[Date]],"yyyy-mm-dd") -> 1_2010-09-17 | O34: =VLOOKUP($N34,Features!A34:N176,4,FALSE) -> 82.11 | P34: =VLOOKUP($N34,Features!A34:N176,11,FALSE) -> 211.52246 | Q34: =VLOOKUP($N34,Features!A34:N176,14,FALSE) -> 0 | R34: =IF(Table2[[#This Row],[3_Week_Forecast]]<Table2[[#This Row],[Weekly_Sales]], "Underforecast", "Overforecast") -> Underforecast | V34: 2012-07 | W34: 66468.79
A35: 1 | B35: 1 | C35: 40445 | D35: 18122.52 | E35: FALSE | F35: =YEAR(Table2[[#This Row],[Date]]) -> 2010 | G35: =TEXT(Table2[[#This Row],[Date]],"mmm") -> Sep | H35: =TEXT(Table2[[#This Row],[Date]],"yyyy-mm") -> 2010-09 | I35: =WEEKNUM(Table2[[#This Row],[Date]]) -> 39 | J35: =Table2[[#This Row],[Weekly_Sales]]*2 -> 36245.04 | K35: =AVERAGE(D32:D34) -> 17930.25 | L35: =Table2[[#This Row],[Weekly_Sales]]-Table2[[#This Row],[3_Week_Forecast]] -> 192.27 | M35: =ABS(Table2[[#This Row],[Forecast Error]]/Table2[[#This Row],[Weekly_Sales]])*100 -> 1.0609452 | N35: =Table2[[#This Row],[Store]] & "_" & TEXT(Table2[[#This Row],[Date]],"yyyy-mm-dd") -> 1_2010-09-24 | O35: =VLOOKUP($N35,Features!A35:N177,4,FALSE) -> 80.94 | P35: =VLOOKUP($N35,Features!A35:N177,11,FALSE) -> 211.59722 | Q35: =VLOOKUP($N35,Features!A35:N177,14,FALSE) -> 0 | R35: =IF(Table2[[#This Row],[3_Week_Forecast]]<Table2[[#This Row],[Weekly_Sales]], "Underforecast", "Overforecast") -> Underforecast | V35: 2012-08 | W35: 83045.57
... A38: 1 | B38: 1 | C38: 40466 | D38: 26978.34 | E38: FALSE | F38: =YEAR(Table2[[#This Row],[Date]]) -> 2010 | G38: =TEXT(Table2[[#This Row],[Date]],"mmm") -> Oct | H38: =TEXT(Table2[[#This Row],[Date]],"yyyy-mm") -> 2010-10 | I38: =WEEKNUM(Table2[[#This Row],[Date]]) -> 42 | J38: =Table2[[#This Row],[Weekly_Sales]]*2 -> 53956.68 | K38: =AVERAGE(D35:D37) -> 20534.913 | L38: =Table2[[#This Row],[Weekly_Sales]]-Table2[[#This Row],[3_Week_Forecast]] -> 6443.4267 | M38: =ABS(Table2[[#This Row],[Forecast Error]]/Table2[[#This Row],[Weekly_Sales]])*100 -> 23.883703 | N38: =Table2[[#This Row],[Store]] & "_" & TEXT(Table2[[#This Row],[Date]],"yyyy-mm-dd") -> 1_2010-10-15 | O38: =VLOOKUP($N38,Features!A38:N180,4,FALSE) -> 67.18 | P38: =VLOOKUP($N38,Features!A38:N180,11,FALSE) -> 211.81374 | Q38: =VLOOKUP($N38,Features!A38:N180,14,FALSE) -> 0 | R38: =IF(Table2[[#This Row],[3_Week_Forecast]]<Table2[[#This Row],[Weekly_Sales]], "Underforecast", "Overforecast") -> Underforecast | V38: Grand Total | W38: 3219405.2
A39: 1 | B39: 1 | C39: 40473 | D39: 25543.04 | E39: FALSE | F39: =YEAR(Table2[[#This Row],[Date]]) -> 2010 | G39: =TEXT(Table2[[#This Row],[Date]],"mmm") -> Oct | H39: =TEXT(Table2[[#This Row],[Date]],"yyyy-mm") -> 2010-10 | I39: =WEEKNUM(Table2[[#This Row],[Date]]) -> 43 | J39: =Table2[[#This Row],[Weekly_Sales]]*2 -> 51086.08 | K39: =AVERAGE(D36:D38) -> 23486.853 | L39: =Table2[[#This Row],[Weekly_Sales]]-Table2[[#This Row],[3_Week_Forecast]] -> 2056.1867 | M39: =ABS(Table2[[#This Row],[Forecast Error]]/Table2[[#This Row],[Weekly_Sales]])*100 -> 8.0498902 | N39: =Table2[[#This Row],[Store]] & "_" & TEXT(Table2[[#This Row],[Date]],"yyyy-mm-dd") -> 1_2010-10-22 | O39: =VLOOKUP($N39,Features!A39:N181,4,FALSE) -> 69.86 | P39: =VLOOKUP($N39,Features!A39:N181,11,FALSE) -> 211.86129 | Q39: =VLOOKUP($N39,Features!A39:N181,14,FALSE) -> 0 | R39: =IF(Table2[[#This Row],[3_Week_Forecast]]<Table2[[#This Row],[Weekly_Sales]], "Underforecast", "Overforecast") -> Underforecast
A40: 1 | B40: 1 | C40: 40480 | D40: 38640.93 | E40: FALSE | F40: =YEAR(Table2[[#This Row],[Date]]) -> 2010 | G40: =TEXT(Table2[[#This Row],[Date]],"mmm") -> Oct | H40: =TEXT(Table2[[#This Row],[Date]],"yyyy-mm") -> 2010-10 | I40: =WEEKNUM(Table2[[#This Row],[Date]]) -> 44 | J40: =Table2[[#This Row],[Weekly_Sales]]*2 -> 77281.86 | K40: =AVERAGE(D37:D39) -> 25303.137 | L40: =Table2[[#This Row],[Weekly_Sales]]-Table2[[#This Row],[3_Week_Forecast]] -> 13337.793 | M40: =ABS(Table2[[#This Row],[Forecast Error]]/Table2[[#This Row],[Weekly_Sales]])*100 -> 34.517268 | N40: =Table2[[#This Row],[Store]] & "_" & TEXT(Table2[[#This Row],[Date]],"yyyy-mm-dd") -> 1_2010-10-29 | O40: =VLOOKUP($N40,Features!A40:N182,4,FALSE) -> 69.64 | P40: =VLOOKUP($N40,Features!A40:N182,11,FALSE) -> 211.90884 | Q40: =VLOOKUP($N40,Features!A40:N182,14,FALSE) -> 0 | R40: =IF(Table2[[#This Row],[3_Week_Forecast]]<Table2[[#This Row],[Weekly_Sales]], "Underforecast", "Overforecast") -> Underforecast
A41: 1 | B41: 1 | C41: 40487 | D41: 34238.88 | E41: FALSE | F41: =YEAR(Table2[[#This Row],[Date]]) -> 2010 | G41: =TEXT(Table2[[#This Row],[Date]],"mmm") -> Nov | H41: =TEXT(Table2[[#This Row],[Date]],"yyyy-mm") -> 2010-11 | I41: =WEEKNUM(Table2[[#This Row],[Date]]) -> 45 | J41: =Table2[[#This Row],[Weekly_Sales]]*2 -> 68477.76 | K41: =AVERAGE(D38:D40) -> 30387.437 | L41: =Table2[[#This Row],[Weekly_Sales]]-Table2[[#This Row],[3_Week_Forecast]] -> 3851.4433 | M41: =ABS(Table2[[#This Row],[Forecast Error]]/Table2[[#This Row],[Weekly_Sales]])*100 -> 11.248742 | N41: =Table2[[#This Row],[Store]] & "_" & TEXT(Table2[[#This Row],[Date]],"yyyy-mm-dd") -> 1_2010-11-05 | O41: =VLOOKUP($N41,Features!A41:N183,4,FALSE) -> 58.74 | P41: =VLOOKUP($N41,Features!A41:N183,11,FALSE) -> 211.95639 | Q41: =VLOOKUP($N41,Features!A41:N183,14,FALSE) -> 0 | R41: =IF(Table2[[#This Row],[3_Week_Forecast]]<Table2[[#This Row],[Weekly_Sales]], "Underforecast", "Overforecast") -> Underforecast
A42: 1 | B42: 1 | C42: 40494 | D42: 19549.39 | E42: FALSE | F42: =YEAR(Table2[[#This Row],[Date]]) -> 2010 | G42: =TEXT(Table2[[#This Row],[Date]],"mmm") -> Nov | H42: =TEXT(Table2[[#This Row],[Date]],"yyyy-mm") -> 2010-11 | I42: =WEEKNUM(Table2[[#This Row],[Date]]) -> 46 | J42: =Table2[[#This Row],[Weekly_Sales]]*2 -> 39098.78 | K42: =AVERAGE(D39:D41) -> 32807.617 | L42: =Table2[[#This Row],[Weekly_Sales]]-Table2[[#This Row],[3_Week_Forecast]] -> -13258.227 | M42: =ABS(Table2[[#This Row],[Forecast Error]]/Table2[[#This Row],[Weekly_Sales]])*100 -> 67.819132 | N42: =Table2[[#This Row],[Store]] & "_" & TEXT(Table2[[#This Row],[Date]],"yyyy-mm-dd") -> 1_2010-11-12 | O42: =VLOOKUP($N42,Features!A42:N184,4,FALSE) -> 59.61 | P42: =VLOOKUP($N42,Features!A42:N184,11,FALSE) -> 212.00394 | Q42: =VLOOKUP($N42,Features!A42:N184,14,FALSE) -> 0 | R42: =IF(Table2[[#This Row],[3_Week_Forecast]]<Table2[[#This Row],[Weekly_Sales]], "Underforecast", "Overforecast") -> Overforecast
A43: 1 | B43: 1 | C43: 40501 | D43: 19552.84 | E43: FALSE | F43: =YEAR(Table2[[#This Row],[Date]]) -> 2010 | G43: =TEXT(Table2[[#This Row],[Date]],"mmm") -> Nov | H43: =TEXT(Table2[[#This Row],[Date]],"yyyy-mm") -> 2010-11 | I43: =WEEKNUM(Table2[[#This Row],[Date]]) -> 47 | J43: =Table2[[#This Row],[Weekly_Sales]]*2 -> 39105.68 | K43: =AVERAGE(D40:D42) -> 30809.733 | L43: =Table2[[#This Row],[Weekly_Sales]]-Table2[[#This Row],[3_Week_Forecast]] -> -11256.893 | M43: =ABS(Table2[[#This Row],[Forecast Error]]/Table2[[#This Row],[Weekly_Sales]])*100 -> 57.571654 | N43: =Table2[[#This Row],[Store]] & "_" & TEXT(Table2[[#This Row],[Date]],"yyyy-mm-dd") -> 1_2010-11-19 | O43: =VLOOKUP($N43,Features!A43:N185,4,FALSE) -> 51.41 | P43: =VLOOKUP($N43,Features!A43:N185,11,FALSE) -> 211.88967 | Q43: =VLOOKUP($N43,Features!A43:N185,14,FALSE) -> 0 | R43: =IF(Table2[[#This Row],[3_Week_Forecast]]<Table2[[#This Row],[Weekly_Sales]], "Underforecast", "Overforecast") -> Overforecast
A44: 1 | B44: 1 | C44: 40508 | D44: 18820.29 | E44: TRUE | F44: =YEAR(Table2[[#This Row],[Date]]) -> 2010 | G44: =TEXT(Table2[[#This Row],[Date]],"mmm") -> Nov | H44: =TEXT(Table2[[#This Row],[Date]],"yyyy-mm") -> 2010-11 | I44: =WEEKNUM(Table2[[#This Row],[Date]]) -> 48 | J44: =Table2[[#This Row],[Weekly_Sales]]*2 -> 37640.58 | K44: =AVERAGE(D41:D43) -> 24447.037 | L44: =Table2[[#This Row],[Weekly_Sales]]-Table2[[#This Row],[3_Week_Forecast]] -> -5626.7467 | M44: =ABS(Table2[[#This Row],[Forecast Error]]/Table2[[#This Row],[Weekly_Sales]])*100 -> 29.897237 | N44: =Table2[[#This Row],[Store]] & "_" & TEXT(Table2[[#This Row],[Date]],"yyyy-mm-dd") -> 1_2010-11-26 | O44: =VLOOKUP($N44,Features!A44:N186,4,FALSE) -> 64.52 | P44: =VLOOKUP($N44,Features!A44:N186,11,FALSE) -> 211.74843 | Q44: =VLOOKUP($N44,Features!A44:N186,14,FALSE) -> 0 | R44: =IF(Table2[[#This Row],[3_Week_Forecast]]<Table2[[#This Row],[Weekly_Sales]], "Underforecast", "Overforecast") -> Overforecast
A45: 1 | B45: 1 | C45: 40515 | D45: 22517.56 | E45: FALSE | F45: =YEAR(Table2[[#This Row],[Date]]) -> 2010 | G45: =TEXT(Table2[[#This Row],[Date]],"mmm") -> Dec | H45: =TEXT(Table2[[#This Row],[Date]],"yyyy-mm") -> 2010-12 | I45: =WEEKNUM(Table2[[#This Row],[Date]]) -> 49 | J45: =Table2[[#This Row],[Weekly_Sales]]*2 -> 45035.12 | K45: =AVERAGE(D42:D44) -> 19307.507 | L45: =Table2[[#This Row],[Weekly_Sales]]-Table2[[#This Row],[3_Week_Forecast]] -> 3210.0533 | M45: =ABS(Table2[[#This Row],[Forecast Error]]/Table2[[#This Row],[Weekly_Sales]])*100 -> 14.255778 | N45: =Table2[[#This Row],[Store]] & "_" & TEXT(Table2[[#This Row],[Date]],"yyyy-mm-dd") -> 1_2010-12-03 | O45: =VLOOKUP($N45,Features!A45:N187,4,FALSE) -> 49.27 | P45: =VLOOKUP($N45,Features!A45:N187,11,FALSE) -> 211.60719 | Q45: =VLOOKUP($N45,Features!A45:N187,14,FALSE) -> 0 | R45: =IF(Table2[[#This Row],[3_Week_Forecast]]<Table2[[#This Row],[Weekly_Sales]], "Underforecast", "Overforecast") -> Underforecast
A46: 1 | B46: 1 | C46: 40522 | D46: 31497.65 | E46: FALSE | F46: =YEAR(Table2[[#This Row],[Date]]) -> 2010 | G46: =TEXT(Table2[[#This Row],[Date]],"mmm") -> Dec | H46: =TEXT(Table2[[#This Row],[Date]],"yyyy-mm") -> 2010-12 | I46: =WEEKNUM(Table2[[#This Row],[Date]]) -> 50 | J46: =Table2[[#This Row],[Weekly_Sales]]*2 -> 62995.3 | K46: =AVERAGE(D43:D45) -> 20296.897 | L46: =Table2[[#This Row],[Weekly_Sales]]-Table2[[#This Row],[3_Week_Forecast]] -> 11200.753 | M46: =ABS(Table2[[#This Row],[Forecast Error]]/Table2[[#This Row],[Weekly_Sales]])*100 -> 35.5606 | N46: =Table2[[#This Row],[Store]] & "_" & TEXT(Table2[[#This Row],[Date]],"yyyy-mm-dd") -> 1_2010-12-10 | O46: =VLOOKUP($N46,Features!A46:N188,4,FALSE) -> 46.33 | P46: =VLOOKUP($N46,Features!A46:N188,11,FALSE) -> 211.46595 | Q46: =VLOOKUP($N46,Features!A46:N188,14,FALSE) -> 0 | R46: =IF(Table2[[#This Row],[3_Week_Forecast]]<Table2[[#This Row],[Weekly_Sales]], "Underforecast", "Overforecast") -> Underforecast
A47: 1 | B47: 1 | C47: 40529 | D47: 44912.86 | E47: FALSE | F47: =YEAR(Table2[[#This Row],[Date]]) -> 2010 | G47: =TEXT(Table2[[#This Row],[Date]],"mmm") -> Dec | H47: =TEXT(Table2[[#This Row],[Date]],"yyyy-mm") -> 2010-12 | I47: =WEEKNUM(Table2[[#This Row],[Date]]) -> 51 | J47: =Table2[[#This Row],[Weekly_Sales]]*2 -> 89825.72 | K47: =AVERAGE(D44:D46) -> 24278.5 | L47: =Table2[[#This Row],[Weekly_Sales]]-Table2[[#This Row],[3_Week_Forecast]] -> 20634.36 | M47: =ABS(Table2[[#This Row],[Forecast Error]]/Table2[[#This Row],[Weekly_Sales]])*100 -> 45.9431 | N47: =Table2[[#This Row],[Store]] & "_" & TEXT(Table2[[#This Row],[Date]],"yyyy-mm-dd") -> 1_2010-12-17 | O47: =VLOOKUP($N47,Features!A47:N189,4,FALSE) -> 49.84 | P47: =VLOOKUP($N47,Features!A47:N189,11,FALSE) -> 211.40531 | Q47: =VLOOKUP($N47,Features!A47:N189,14,FALSE) -> 0 | R47: =IF(Table2[[#This Row],[3_Week_Forecast]]<Table2[[#This Row],[Weekly_Sales]], "Underforecast", "Overforecast") -> Underforecast
A48: 1 | B48: 1 | C48: 40536 | D48: 55931.23 | E48: FALSE | F48: =YEAR(Table2[[#This Row],[Date]]) -> 2010 | G48: =TEXT(Table2[[#This Row],[Date]],"mmm") -> Dec | H48: =TEXT(Table2[[#This Row],[Date]],"yyyy-mm") -> 2010-12 | I48: =WEEKNUM(Table2[[#This Row],[Date]]) -> 52 | J48: =Table2[[#This Row],[Weekly_Sales]]*2 -> 111862.46 | K48: =AVERAGE(D45:D47) -> 32976.023 | L48: =Table2[[#This Row],[Weekly_Sales]]-Table2[[#This Row],[3_Week_Forecast]] -> 22955.207 | M48: =ABS(Table2[[#This Row],[Forecast Error]]/Table2[[#This Row],[Weekly_Sales]])*100 -> 41.041841 | N48: =Table2[[#This Row],[Store]] & "_" & TEXT(Table2[[#This Row],[Date]],"yyyy-mm-dd") -> 1_2010-12-24 | O48: =VLOOKUP($N48,Features!A48:N190,4,FALSE) -> 52.33 | P48: =VLOOKUP($N48,Features!A48:N190,11,FALSE) -> 211.40512 | Q48: =VLOOKUP($N48,Features!A48:N190,14,FALSE) -> 0 | R48: =IF(Table2[[#This Row],[3_Week_Forecast]]<Table2[[#This Row],[Weekly_Sales]], "Underforecast", "Overforecast") -> Underforecast
A49: 1 | B49: 1 | C49: 40543 | D49: 19124.58 | E49: TRUE | F49: =YEAR(Table2[[#This Row],[Date]]) -> 2010 | G49: =TEXT(Table2[[#This Row],[Date]],"mmm") -> Dec | H49: =TEXT(Table2[[#This Row],[Date]],"yyyy-mm") -> 2010-12 | I49: =WEEKNUM(Table2[[#This Row],[Date]]) -> 53 | J49: =Table2[[#This Row],[Weekly_Sales]]*2 -> 38249.16 | K49: =AVERAGE(D46:D48) -> 44113.913 | L49: =Table2[[#This Row],[Weekly_Sales]]-Table2[[#This Row],[3_Week_Forecast]] -> -24989.333 | M49: =ABS(Table2[[#This Row],[Forecast Error]]/Table2[[#This Row],[Weekly_Sales]])*100 -> 130.66605 | N49: =Table2[[#This Row],[Store]] & "_" & TEXT(Table2[[#This Row],[Date]],"yyyy-mm-dd") -> 1_2010-12-31 | O49: =VLOOKUP($N49,Features!A49:N191,4,FALSE) -> 48.43 | P49: =VLOOKUP($N49,Features!A49:N191,11,FALSE) -> 211.40493 | Q49: =VLOOKUP($N49,Features!A49:N191,14,FALSE) -> 0 | R49: =IF(Table2[[#This Row],[3_Week_Forecast]]<Table2[[#This Row],[Weekly_Sales]], "Underforecast", "Overforecast") -> Overforecast
A50: 1 | B50: 1 | C50: 40550 | D50: 15984.24 | E50: FALSE | F50: =YEAR(Table2[[#This Row],[Date]]) -> 2011 | G50: =TEXT(Table2[[#This Row],[Date]],"mmm") -> Jan | H50: =TEXT(Table2[[#This Row],[Date]],"yyyy-mm") -> 2011-01 | I50: =WEEKNUM(Table2[[#This Row],[Date]]) -> 2 | J50: =Table2[[#This Row],[Weekly_Sales]]*2 -> 31968.48 | K50: =AVERAGE(D47:D49) -> 39989.557 | L50: =Table2[[#This Row],[Weekly_Sales]]-Table2[[#This Row],[3_Week_Forecast]] -> -24005.317 | M50: =ABS(Table2[[#This Row],[Forecast Error]]/Table2[[#This Row],[Weekly_Sales]])*100 -> 150.18116 | N50: =Table2[[#This Row],[Store]] & "_" & TEXT(Table2[[#This Row],[Date]],"yyyy-mm-dd") -> 1_2011-01-07 | O50: =VLOOKUP($N50,Features!A50:N192,4,FALSE) -> 48.27 | P50: =VLOOKUP($N50,Features!A50:N192,11,FALSE) -> 211.40474 | Q50: =VLOOKUP($N50,Features!A50:N192,14,FALSE) -> 0 | R50: =IF(Table2[[#This Row],[3_Week_Forecast]]<Table2[[#This Row],[Weekly_Sales]], "Underforecast", "Overforecast") -> Overforecast
... A144: 1 | B144: 1 | C144: 41208 | D144: 27390.81 | E144: FALSE | F144: =YEAR(Table2[[#This Row],[Date]]) -> 2012 | G144: =TEXT(Table2[[#This Row],[Date]],"mmm") -> Oct | H144: =TEXT(Table2[[#This Row],[Date]],"yyyy-mm") -> 2012-10 | I144: =WEEKNUM(Table2[[#This Row],[Date]]) -> 43 | J144: =Table2[[#This Row],[Weekly_Sales]]*2 -> 54781.62 | K144: =AVERAGE(D141:D143) -> 22951.25 | L144: =Table2[[#This Row],[Weekly_Sales]]-Table2[[#This Row],[3_Week_Forecast]] -> 4439.56 | M144: =ABS(Table2[[#This Row],[Forecast Error]]/Table2[[#This Row],[Weekly_Sales]])*100 -> 16.20821 | N144: =Table2[[#This Row],[Store]] & "_" & TEXT(Table2[[#This Row],[Date]],"yyyy-mm-dd") -> 1_2012-10-26 | O144: =VLOOKUP($N144,Features!A144:N286,4,FALSE) -> 69.16 | P144: =VLOOKUP($N144,Features!A144:N286,11,FALSE) -> 223.44425 | Q144: =VLOOKUP($N144,Features!A144:N286,14,FALSE) -> 4985.77 | R144: =IF(Table2[[#This Row],[3_Week_Forecast]]<Table2[[#This Row],[Weekly_Sales]], "Underforecast", "Overforecast") -> Underforecast

Sheet Features
A1: Store_Date_Key | B1: Store | C1: Date | D1: Temperature | E1: Fuel_Price | F1: MarkDown1 | G1: MarkDown2 | H1: MarkDown3 | I1: MarkDown4 | J1: MarkDown5 | K1: CPI | L1: Unemployment | M1: IsHoliday | N1: Total Markdown
A2: =B2 & "_" & TEXT(C2,"yyyy-mm-dd") -> 1_2010-02-05 | B2: 1 | C2: 40214 | D2: 42.31 | E2: 2.572 | F2: NA | G2: NA | H2: NA | I2: NA | J2: NA | K2: 211.09636 | L2: 8.106 | M2: FALSE | N2: 0
A3: =B3 & "_" & TEXT(C3,"yyyy-mm-dd") -> 1_2010-02-12 | B3: 1 | C3: 40221 | D3: 38.51 | E3: 2.548 | F3: NA | G3: NA | H3: NA | I3: NA | J3: NA | K3: 211.24217 | L3: 8.106 | M3: TRUE | N3: 0
A4: =B4 & "_" & TEXT(C4,"yyyy-mm-dd") -> 1_2010-02-19 | B4: 1 | C4: 40228 | D4: 39.93 | E4: 2.514 | F4: NA | G4: NA | H4: NA | I4: NA | J4: NA | K4: 211.28914 | L4: 8.106 | M4: FALSE | N4: 0
A5: =B5 & "_" & TEXT(C5,"yyyy-mm-dd") -> 1_2010-02-26 | B5: 1 | C5: 40235 | D5: 46.63 | E5: 2.561 | F5: NA | G5: NA | H5: NA | I5: NA | J5: NA | K5: 211.31964 | L5: 8.106 | M5: FALSE | N5: 0
A6: =B6 & "_" & TEXT(C6,"yyyy-mm-dd") -> 1_2010-03-05 | B6: 1 | C6: 40242 | D6: 46.5 | E6: 2.625 | F6: NA | G6: NA | H6: NA | I6: NA | J6: NA | K6: 211.35014 | L6: 8.106 | M6: FALSE | N6: 0
A7: =B7 & "_" & TEXT(C7,"yyyy-mm-dd") -> 1_2010-03-12 | B7: 1 | C7: 40249 | D7: 57.79 | E7: 2.667 | F7: NA | G7: NA | H7: NA | I7: NA | J7: NA | K7: 211.38064 | L7: 8.106 | M7: FALSE | N7: 0
A8: =B8 & "_" & TEXT(C8,"yyyy-mm-dd") -> 1_2010-03-19 | B8: 1 | C8: 40256 | D8: 54.58 | E8: 2.72 | F8: NA | G8: NA | H8: NA | I8: NA | J8: NA | K8: 211.21563 | L8: 8.106 | M8: FALSE | N8: 0
A9: =B9 & "_" & TEXT(C9,"yyyy-mm-dd") -> 1_2010-03-26 | B9: 1 | C9: 40263 | D9: 51.45 | E9: 2.732 | F9: NA | G9: NA | H9: NA | I9: NA | J9: NA | K9: 211.01804 | L9: 8.106 | M9: FALSE | N9: 0
A10: =B10 & "_" & TEXT(C10,"yyyy-mm-dd") -> 1_2010-04-02 | B10: 1 | C10: 40270 | D10: 62.27 | E10: 2.719 | F10: NA | G10: NA | H10: NA | I10: NA | J10: NA | K10: 210.82045 | L10: 7.808 | M10: FALSE | N10: 0
A11: =B11 & "_" & TEXT(C11,"yyyy-mm-dd") -> 1_2010-04-09 | B11: 1 | C11: 40277 | D11: 65.86 | E11: 2.77 | F11: NA | G11: NA | H11: NA | I11: NA | J11: NA | K11: 210.62286 | L11: 7.808 | M11: FALSE | N11: 0
A12: =B12 & "_" & TEXT(C12,"yyyy-mm-dd") -> 1_2010-04-16 | B12: 1 | C12: 40284 | D12: 66.32 | E12: 2.808 | F12: NA | G12: NA | H12: NA | I12: NA | J12: NA | K12: 210.4887 | L12: 7.808 | M12: FALSE | N12: 0
A13: =B13 & "_" & TEXT(C13,"yyyy-mm-dd") -> 1_2010-04-23 | B13: 1 | C13: 40291 | D13: 64.84 | E13: 2.795 | F13: NA | G13: NA | H13: NA | I13: NA | J13: NA | K13: 210.43912 | L13: 7.808 | M13: FALSE | N13: 0
... A93: =B93 & "_" & TEXT(C93,"yyyy-mm-dd") -> 1_2011-11-04 | B93: 1 | C93: 40851 | D93: 54.98 | E93: 3.332 | F93: NA | G93: NA | H93: NA | I93: NA | J93: NA | K93: 217.83738 | L93: 7.866 | M93: FALSE | N93: 0
A94: =B94 & "_" & TEXT(C94,"yyyy-mm-dd") -> 1_2011-11-11 | B94: 1 | C94: 40858 | D94: 59.11 | E94: 3.297 | F94: 10382.9 | G94: 6115.67 | H94: 215.07 | I94: 2406.62 | J94: 6551.42 | K94: 217.99808 | L94: 7.866 | M94: FALSE | N94: 25671.68
A95: =B95 & "_" & TEXT(C95,"yyyy-mm-dd") -> 1_2011-11-18 | B95: 1 | C95: 40865 | D95: 62.25 | E95: 3.308 | F95: 6074.12 | G95: 254.39 | H95: 51.98 | I95: 427.39 | J95: 5988.57 | K95: 218.22051 | L95: 7.866 | M95: FALSE | N95: 12796.45
A96: =B96 & "_" & TEXT(C96,"yyyy-mm-dd") -> 1_2011-11-25 | B96: 1 | C96: 40872 | D96: 60.14 | E96: 3.236 | F96: 410.31 | G96: 98 | H96: 55805.51 | I96: 8 | J96: 554.92 | K96: 218.46762 | L96: 7.866 | M96: TRUE | N96: 56876.74
A97: =B97 & "_" & TEXT(C97,"yyyy-mm-dd") -> 1_2011-12-02 | B97: 1 | C97: 40879 | D97: 48.91 | E97: 3.172 | F97: 5629.51 | G97: 68 | H97: 1398.11 | I97: 2084.64 | J97: 20475.32 | K97: 218.71473 | L97: 7.866 | M97: FALSE | N97: 29655.58
A98: =B98 & "_" & TEXT(C98,"yyyy-mm-dd") -> 1_2011-12-09 | B98: 1 | C98: 40886 | D98: 43.93 | E98: 3.158 | F98: 4640.65 | G98: 19 | H98: 105.02 | I98: 3639.42 | J98: 14461.82 | K98: 218.96185 | L98: 7.866 | M98: FALSE | N98: 22865.91
A99: =B99 & "_" & TEXT(C99,"yyyy-mm-dd") -> 1_2011-12-16 | B99: 1 | C99: 40893 | D99: 51.63 | E99: 3.159 | F99: 5011.32 | G99: 67 | H99: 347.37 | I99: 225.79 | J99: 4011.37 | K99: 219.17945 | L99: 7.866 | M99: FALSE | N99: 9662.85
A100: =B100 & "_" & TEXT(C100,"yyyy-mm-dd") -> 1_2011-12-23 | B100: 1 | C100: 40900 | D100: 47.96 | E100: 3.112 | F100: 2725.36 | G100: 40.48 | H100: 634.7 | I100: 24.9 | J100: 2739.43 | K100: 219.35772 | L100: 7.866 | M100: FALSE | N100: 6164.87
A101: =B101 & "_" & TEXT(C101,"yyyy-mm-dd") -> 1_2011-12-30 | B101: 1 | C101: 40907 | D101: 44.55 | E101: 3.129 | F101: 5762.1 | G101: 46011.38 | H101: 260.36 | I101: 983.65 | J101: 4735.78 | K101: 219.53599 | L101: 7.866 | M101: TRUE | N101: 57753.27
A102: =B102 & "_" & TEXT(C102,"yyyy-mm-dd") -> 1_2012-01-06 | B102: 1 | C102: 40914 | D102: 49.01 | E102: 3.157 | F102: 6277.39 | G102: 21813.16 | H102: 143.1 | I102: 1450.13 | J102: 8483 | K102: 219.71426 | L102: 7.348 | M102: FALSE | N102: 38166.78
A103: =B103 & "_" & TEXT(C103,"yyyy-mm-dd") -> 1_2012-01-13 | B103: 1 | C103: 40921 | D103: 48.53 | E103: 3.261 | F103: 5183.29 | G103: 8025.87 | H103: 42.24 | I103: 453.08 | J103: 3719.38 | K103: 219.89253 | L103: 7.348 | M103: FALSE | N103: 17423.86
A104: =B104 & "_" & TEXT(C104,"yyyy-mm-dd") -> 1_2012-01-20 | B104: 1 | C104: 40928 | D104: 54.11 | E104: 3.268 | F104: 4139.87 | G104: 2807.19 | H104: 33.88 | I104: 500.62 | J104: 3400.21 | K104: 219.98569 | L104: 7.348 | M104: FALSE | N104: 10881.77
A105: =B105 & "_" & TEXT(C105,"yyyy-mm-dd") -> 1_2012-01-27 | B105: 1 | C105: 40935 | D105: 54.26 | E105: 3.29 | F105: 1164.46 | G105: 1082.74 | H105: 44 | I105: 11 | J105: 1222.19 | K105: 220.07885 | L105: 7.348 | M105: FALSE | N105: 3524.39
... A114: =B114 & "_" & TEXT(C114,"yyyy-mm-dd") -> 1_2012-03-30 | B114: 1 | C114: 40998 | D114: 67.61 | E114: 3.845 | F114: 10309.58 | G114: 0.5 | H114: 10.25 | I114: 1654.17 | J114: 2642.78 | K114: 221.36101 | L114: 7.348 | M114: FALSE | N114: 14617.28
A115: =B115 & "_" & TEXT(C115,"yyyy-mm-dd") -> 1_2012-04-06 | B115: 1 | C115: 41005 | D115: 70.43 | E115: 3.891 | F115: 10121.97 | G115: NA | H115: 77.98 | I115: 3750.59 | J115: 4510.72 | K115: 221.43561 | L115: 7.143 | M115: FALSE | N115: 18461.26
A116: =B116 & "_" & TEXT(C116,"yyyy-mm-dd") -> 1_2012-04-13 | B116: 1 | C116: 41012 | D116: 69.07 | E116: 3.891 | F116: 6186.19 | G116: 3288.69 | H116: 17.07 | I116: 1822.55 | J116: 1063.78 | K116: 221.51021 | L116: 7.143 | M116: FALSE | N116: 12378.28
A117: =B117 & "_" & TEXT(C117,"yyyy-mm-dd") -> 1_2012-04-20 | B117: 1 | C117: 41019 | D117: 66.76 | E117: 3.877 | F117: 2230.8 | G117: 612.02 | H117: 19.75 | I117: 275.13 | J117: 5747.1 | K117: 221.56407 | L117: 7.143 | M117: FALSE | N117: 8884.8
A118: =B118 & "_" & TEXT(C118,"yyyy-mm-dd") -> 1_2012-04-27 | B118: 1 | C118: 41026 | D118: 67.23 | E118: 3.814 | F118: 3221.25 | G118: NA | H118: 35.49 | I118: 577.14 | J118: 6222.25 | K118: 221.61794 | L118: 7.143 | M118: FALSE | N118: 10056.13
A119: =B119 & "_" & TEXT(C119,"yyyy-mm-dd") -> 1_2012-05-04 | B119: 1 | C119: 41033 | D119: 75.55 | E119: 3.749 | F119: 21290.13 | G119: NA | H119: 69.89 | I119: 4977.35 | J119: 3261.04 | K119: 221.6718 | L119: 7.143 | M119: FALSE | N119: 29598.41
A120: =B120 & "_" & TEXT(C120,"yyyy-mm-dd") -> 1_2012-05-11 | B120: 1 | C120: 41040 | D120: 73.77 | E120: 3.688 | F120: 8351.4 | G120: NA | H120: 10.52 | I120: 2443.14 | J120: 3127.88 | K120: 221.72566 | L120: 7.143 | M120: FALSE | N120: 13932.94
A121: =B121 & "_" & TEXT(C121,"yyyy-mm-dd") -> 1_2012-05-18 | B121: 1 | C121: 41047 | D121: 70.33 | E121: 3.63 | F121: 6154.14 | G121: NA | H121: 45.11 | I121: 1675.49 | J121: 5508.18 | K121: 221.74267 | L121: 7.143 | M121: FALSE | N121: 13382.92
A122: =B122 & "_" & TEXT(C122,"yyyy-mm-dd") -> 1_2012-05-25 | B122: 1 | C122: 41054 | D122: 77.22 | E122: 3.561 | F122: 4039.39 | G122: NA | H122: 745.19 | I122: 1429.96 | J122: 3631.13 | K122: 221.74494 | L122: 7.143 | M122: FALSE | N122: 9845.67
A123: =B123 & "_" & TEXT(C123,"yyyy-mm-dd") -> 1_2012-06-01 | B123: 1 | C123: 41061 | D123: 77.95 | E123: 3.501 | F123: 6086.21 | G123: 12 | H123: 370.51 | I123: 148.75 | J123: 3690.85 | K123: 221.74721 | L123: 7.143 | M123: FALSE | N123: 10308.32
A124: =B124 & "_" & TEXT(C124,"yyyy-mm-dd") -> 1_2012-06-08 | B124: 1 | C124: 41068 | D124: 78.3 | E124: 3.452 | F124: 8813.81 | G124: 116.8 | H124: 64.55 | I124: 2652.04 | J124: 7161.91 | K124: 221.74948 | L124: 7.143 | M124: FALSE | N124: 18809.11
A125: =B125 & "_" & TEXT(C125,"yyyy-mm-dd") -> 1_2012-06-15 | B125: 1 | C125: 41075 | D125: 79.35 | E125: 3.393 | F125: 5621.99 | G125: 109.6 | H125: 0.25 | I125: 2420.28 | J125: 3083.26 | K125: 221.76264 | L125: 7.143 | M125: FALSE | N125: 11235.38
A126: =B126 & "_" & TEXT(C126,"yyyy-mm-dd") -> 1_2012-06-22 | B126: 1 | C126: 41082 | D126: 78.39 | E126: 3.346 | F126: 8624.56 | G126: 171.25 | H126: 3.05 | I126: 2524.07 | J126: 7063.68 | K126: 221.80302 | L126: 7.143 | M126: FALSE | N126: 18386.61
A127: =B127 & "_" & TEXT(C127,"yyyy-mm-dd") -> 1_2012-06-29 | B127: 1 | C127: 41089 | D127: 84.88 | E127: 3.286 | F127: 3965.73 | G127: 161.6 | H127: NA | I127: 435.99 | J127: 4212.97 | K127: 221.8434 | L127: 7.143 | M127: FALSE | N127: 8776.29
A128: =B128 & "_" & TEXT(C128,"yyyy-mm-dd") -> 1_2012-07-06 | B128: 1 | C128: 41096 | D128: 81.57 | E128: 3.227 | F128: 12218.76 | G128: 94.4 | H128: 192.83 | I128: 4066.01 | J128: 6149.04 | K128: 221.88378 | L128: 6.908 | M128: FALSE | N128: 22721.04
A129: =B129 & "_" & TEXT(C129,"yyyy-mm-dd") -> 1_2012-07-13 | B129: 1 | C129: 41103 | D129: 77.12 | E129: 3.256 | F129: 7218.13 | G129: 45.2 | H129: 36.24 | I129: 3909.38 | J129: 2596.37 | K129: 221.92416 | L129: 6.908 | M129: FALSE | N129: 13805.32
A130: =B130 & "_" & TEXT(C130,"yyyy-mm-dd") -> 1_2012-07-20 | B130: 1 | C130: 41110 | D130: 80.42 | E130: 3.311 | F130: 3213 | G130: 313.72 | H130: 9.53 | I130: 2262.02 | J130: 3228.19 | K130: 221.93273 | L130: 6.908 | M130: FALSE | N130: 9026.46
A131: =B131 & "_" & TEXT(C131,"yyyy-mm-dd") -> 1_2012-07-27 | B131: 1 | C131: 41117 | D131: 82.66 | E131: 3.407 | F131: 7146.9 | G131: 389.02 | H131: 1.59 | I131: 10267.54 | J131: 4325.19 | K131: 221.9413 | L131: 6.908 | M131: FALSE | N131: 22130.24
A132: =B132 & "_" & TEXT(C132,"yyyy-mm-dd") -> 1_2012-08-03 | B132: 1 | C132: 41124 | D132: 86.11 | E132: 3.417 | F132: 27584.78 | G132: 119.98 | H132: 30.23 | I132: 12007.04 | J132: 4661.71 | K132: 221.94986 | L132: 6.908 | M132: FALSE | N132: 44403.74
A133: =B133 & "_" & TEXT(C133,"yyyy-mm-dd") -> 1_2012-08-10 | B133: 1 | C133: 41131 | D133: 85.05 | E133: 3.494 | F133: 11436.22 | G133: 245 | H133: 6.85 | I133: 6964.26 | J133: 4836.22 | K133: 221.95843 | L133: 6.908 | M133: FALSE | N133: 23488.55
A134: =B134 & "_" & TEXT(C134,"yyyy-mm-dd") -> 1_2012-08-17 | B134: 1 | C134: 41138 | D134: 84.85 | E134: 3.571 | F134: 3662.06 | G134: 137.86 | H134: 4.84 | I134: 2752.2 | J134: 3446.15 | K134: 222.03841 | L134: 6.908 | M134: FALSE | N134: 10003.11
A135: =B135 & "_" & TEXT(C135,"yyyy-mm-dd") -> 1_2012-08-24 | B135: 1 | C135: 41145 | D135: 77.66 | E135: 3.62 | F135: 6237.83 | G135: 260.06 | H135: 2.97 | I135: 3463.03 | J135: 7988.25 | K135: 222.17195 | L135: 6.908 | M135: FALSE | N135: 17952.14
A136: =B136 & "_" & TEXT(C136,"yyyy-mm-dd") -> 1_2012-08-31 | B136: 1 | C136: 41152 | D136: 80.49 | E136: 3.638 | F136: 21442.73 | G136: 102.32 | H136: 21.7 | I136: 13209.64 | J136: 3032.96 | K136: 222.30548 | L136: 6.908 | M136: FALSE | N136: 37809.35
A137: =B137 & "_" & TEXT(C137,"yyyy-mm-dd") -> 1_2012-09-07 | B137: 1 | C137: 41159 | D137: 83.96 | E137: 3.73 | F137: 5204.68 | G137: 35.74 | H137: 50.94 | I137: 4120.32 | J137: 2737.17 | K137: 222.43902 | L137: 6.908 | M137: TRUE | N137: 12148.85
A138: =B138 & "_" & TEXT(C138,"yyyy-mm-dd") -> 1_2012-09-14 | B138: 1 | C138: 41166 | D138: 74.97 | E138: 3.717 | F138: 17212.52 | G138: 7 | H138: 18.79 | I138: 1523.11 | J138: 7992.72 | K138: 222.58202 | L138: 6.908 | M138: FALSE | N138: 26754.14
A139: =B139 & "_" & TEXT(C139,"yyyy-mm-dd") -> 1_2012-09-21 | B139: 1 | C139: 41173 | D139: 69.87 | E139: 3.721 | F139: 6352.3 | G139: 7.64 | H139: 4.69 | I139: 1010.06 | J139: 6456.71 | K139: 222.78184 | L139: 6.908 | M139: FALSE | N139: 13831.4
A140: =B140 & "_" & TEXT(C140,"yyyy-mm-dd") -> 1_2012-09-28 | B140: 1 | C140: 41180 | D140: 76.08 | E140: 3.666 | F140: 3666.27 | G140: 7.64 | H140: 1.65 | I140: 1417.96 | J140: 4744.28 | K140: 222.98166 | L140: 6.908 | M140: FALSE | N140: 9837.8
A141: =B141 & "_" & TEXT(C141,"yyyy-mm-dd") -> 1_2012-10-05 | B141: 1 | C141: 41187 | D141: 68.55 | E141: 3.617 | F141: 8077.89 | G141: NA | H141: 18.22 | I141: 3617.43 | J141: 3626.14 | K141: 223.18148 | L141: 6.573 | M141: FALSE | N141: 15339.68
A142: =B142 & "_" & TEXT(C142,"yyyy-mm-dd") -> 1_2012-10-12 | B142: 1 | C142: 41194 | D142: 62.99 | E142: 3.601 | F142: 2086.18 | G142: NA | H142: 8.11 | I142: 602.36 | J142: 5926.45 | K142: 223.3813 | L142: 6.573 | M142: FALSE | N142: 8623.1
A143: =B143 & "_" & TEXT(C143,"yyyy-mm-dd") -> 1_2012-10-19 | B143: 1 | C143: 41201 | D143: 67.97 | E143: 3.594 | F143: 950.33 | G143: NA | H143: 4.93 | I143: 80.25 | J143: 2312.85 | K143: 223.42572 | L143: 6.573 | M143: FALSE | N143: 3348.36
A144: =B144 & "_" & TEXT(C144,"yyyy-mm-dd") -> 1_2012-10-26 | B144: 1 | C144: 41208 | D144: 69.16 | E144: 3.506 | F144: 2585.85 | G144: 31.75 | H144: 6 | I144: 1057.16 | J144: 1305.01 | K144: 223.44425 | L144: 6.573 | M144: FALSE | N144: 4985.77
